pytranscoder/__init__.py
pytranscoder/__main__.py
pytranscoder/agent.py
pytranscoder/cluster.py
pytranscoder/config.py
pytranscoder/ffmpeg.py
pytranscoder/media.py
pytranscoder/processor.py
pytranscoder/profile.py
pytranscoder/rule.py
pytranscoder/template.py
pytranscoder/transcode.py
pytranscoder/utils.py
pytranscoder_ffmpeg-2.2.7.data/data/share/doc/pytranscoder/Cluster.md
pytranscoder_ffmpeg-2.2.7.data/data/share/doc/pytranscoder/README.md
pytranscoder_ffmpeg-2.2.7.data/data/share/doc/pytranscoder/cluster-sample.yml
pytranscoder_ffmpeg-2.2.7.data/data/share/doc/pytranscoder/simple.yml
pytranscoder_ffmpeg-2.2.7.data/data/share/doc/pytranscoder/transcode-sample2.yml
pytranscoder_ffmpeg-2.2.7.data/data/share/doc/pytranscoder/transcode.yml
pytranscoder_ffmpeg-2.2.7.dist-info/LICENSE
pytranscoder_ffmpeg-2.2.7.dist-info/METADATA
pytranscoder_ffmpeg-2.2.7.dist-info/WHEEL
pytranscoder_ffmpeg-2.2.7.dist-info/entry_points.txt
pytranscoder_ffmpeg-2.2.7.dist-info/top_level.txt
pytranscoder_ffmpeg-2.2.7.dist-info/RECORD
