Metadata-Version: 2.1
Name: pytranscoder-ffmpeg
Version: 2.2.7
Summary: A ffmpeg workflow manager for transcoding
Home-page: https://github.com/mlsmithjr/transcoder
Author: Marshall L Smith Jr
Author-email: marshallsmithjr@gmail.com
License: UNKNOWN
Keywords: ffmpeg qsv cuda encode transcode
Platform: UNKNOWN
Classifier: Programming Language :: Python :: 3
Classifier: Environment :: Console
Classifier: Topic :: Multimedia :: Video :: Conversion
Classifier: License :: OSI Approved :: GNU General Public License v3 (GPLv3)
Classifier: Intended Audience :: End Users/Desktop
Classifier: Natural Language :: English
Classifier: Operating System :: POSIX :: Linux
Classifier: Operating System :: MacOS :: MacOS X
Classifier: Operating System :: Microsoft :: Windows :: Windows 10
Requires-Python: >=3.7
License-File: LICENSE
Requires-Dist: crayons
Requires-Dist: pyyaml (>=5.1)
